README.md
setup.cfg
setup.py
afb_search/__init__.py
afb_search/__main__.py
afb_search.egg-info/PKG-INFO
afb_search.egg-info/SOURCES.txt
afb_search.egg-info/dependency_links.txt
afb_search.egg-info/entry_points.txt
afb_search.egg-info/requires.txt
afb_search.egg-info/top_level.txt