Metadata-Version: 1.0
Name: afb-search
Version: 1.0.1
Summary: CLI to search enrolled Alexa for Business Devices
Home-page: https://github.com/sodle/afb_search
Author: Scott Odle
Author-email: scott@sjodle.com
License: GPL v3
Platform: UNKNOWN
